cobanov/__init__.py
cobanov/main.py
cobanov-1.2.2.dist-info/LICENSE
cobanov-1.2.2.dist-info/METADATA
cobanov-1.2.2.dist-info/WHEEL
cobanov-1.2.2.dist-info/entry_points.txt
cobanov-1.2.2.dist-info/top_level.txt
cobanov-1.2.2.dist-info/RECORD
