Metadata-Version: 2.1
Name: cobanov
Version: 1.2.2
Summary: Cobanov command line tool
Home-page: https://github.com/cobanov/cobanov-cli
Author: Mert Cobanov
Author-email: mertcobanov@gmail.com
Classifier: Programming Language :: Python :: 3
Classifier: License :: OSI Approved :: MIT License
Classifier: Operating System :: OS Independent
Requires-Python: >=3.6
License-File: LICENSE
Requires-Dist: psutil
Requires-Dist: rich
Requires-Dist: pyudev ; platform_system == "Linux"
